MANIFEST.in
README.rst
setup.py
ivencloud/__init__.py
ivencloud/api.py
ivencloud/models.py
ivencloud.egg-info/PKG-INFO
ivencloud.egg-info/SOURCES.txt
ivencloud.egg-info/dependency_links.txt
ivencloud.egg-info/requires.txt
ivencloud.egg-info/top_level.txt