Metadata-Version: 1.1
Name: ivencloud
Version: 0.2.0
Summary: connect your device to iven cloud
Home-page: https://github.com/IvenProductCloud/PythonSDK
Author: Berk Ozdilek
Author-email: biozdilek@gmail.com
License: MIT
Keywords: iven iot
Platform: UNKNOWN
Classifier: Programming Language :: Python :: 2.7
Classifier: Development Status :: 3 - Alpha
